{"cameraMode":{"drawMode":0,"name":"Shaded","section":"Shading Mode"},"sceneLighting":true,"audioPlay":false,"sceneViewState":{"m_AlwaysRefresh":false,"showFog":true,"showSkybox":true,"showFlares":true,"showImageEffects":true,"showParticleSystems":true,"showVisualEffectGraphs":true,"m_FxEnabled":true},"in2DMode":false,"pivot":{"x":7.8608856201171879,"y":6.986671447753906,"z":1.2690391540527344},"rotation":{"x":-0.21943435072898866,"y":-0.18653808534145356,"z":0.04241348057985306,"w":-0.957101047039032},"size":10.0,"orthographic":false}